briefconf/__init__.py
briefconf/config_handle.py
briefconf/v0/__init__.py
briefconf-0.1.4.dist-info/METADATA
briefconf-0.1.4.dist-info/WHEEL
briefconf-0.1.4.dist-info/RECORD
