Metadata-Version: 2.4
Name: briefconf
Version: 0.1.4
Summary: A lightweight configuration base class for small to medium-sized Python projects.
Author-email: AhFei <vgamebox@outlook.com>
License: MIT
Classifier: Operating System :: OS Independent
Classifier: Programming Language :: Python :: 3
Requires-Python: >=3.11
Requires-Dist: ruamel-yaml>=0.18.14
